LICENSE
omniunibot/__init__.py
omniunibot/client/client.py
omniunibot/common/constants.py
omniunibot/common/data_type.py
omniunibot/connector/base.py
omniunibot/connector/dingtalk.py
omniunibot/connector/lark.py
omniunibot/connector/slack.py
omniunibot/server/__main__.py
omniunibot/server/server.py
omniunibot-0.5.0.dist-info/LICENSE
omniunibot-0.5.0.dist-info/METADATA
omniunibot-0.5.0.dist-info/WHEEL
omniunibot-0.5.0.dist-info/RECORD
