Metadata-Version: 2.1
Name: omniunibot
Version: 0.5.0
Summary: A universal multiplatform message bot
Home-page: https://github.com/yttty/omniunibot
License: MIT
Author: yttty
Author-email: yttty@noreply.com
Requires-Python: >=3.12,<4.0
Classifier: License :: OSI Approved :: MIT License
Classifier: Programming Language :: Python :: 3
Classifier: Programming Language :: Python :: 3.12
Classifier: Programming Language :: Python :: 3.13
Requires-Dist: aiohttp (>=3.9,<4.0)
Requires-Dist: loguru (>=0.6,<0.8)
Requires-Dist: pyzmq (>=26.0,<27.0)
Requires-Dist: slack-sdk (>=3.21)
Project-URL: Repository, https://github.com/yttty/omniunibot
